{
  "_class": "rectangle",
  "booleanOperation": 0,
  "do_objectID": "4657C08F-1859-41FC-BE90-4021E1E7169A",
  "edited": false,
  "exportOptions": {
    "_class": "exportOptions",
    "exportFormats": [
    ],
    "includedLayerIds": [
    ],
    "layerOptions": 0,
    "shouldTrim": false
  },
  "fixedRadius": 0,
  "frame": {
    "_class": "rect",
    "constrainProportions": false,
    "do_objectID": "83CA3828-4E42-4227-B78C-D7FCE44BBDA5",
    "height": 2,
    "width": 576,
    "x": 0,
    "y": 0
  },
  "hasConvertedToNewRoundCorners": true,
  "isFlippedHorizontal": false,
  "isFlippedVertical": false,
  "isLocked": false,
  "isVisible": true,
  "layerListExpandedType": 0,
  "name": "Rectangle 23",
  "nameIsFixed": false,
  "path": {
    "_class": "path",
    "isClosed": true,
    "points": [
      {
        "_class": "curvePoint",
        "cornerRadius": 0,
        "curveFrom": "{0, 0}",
        "curveMode": 1,
        "curveTo": "{0, 0}",
        "hasCurveFrom": false,
        "hasCurveTo": false,
        "point": "{0, 0}"
      },
      {
        "_class": "curvePoint",
        "cornerRadius": 0,
        "curveFrom": "{0, 1}",
        "curveMode": 1,
        "curveTo": "{0, 1}",
        "hasCurveFrom": false,
        "hasCurveTo": false,
        "point": "{0, 1}"
      },
      {
        "_class": "curvePoint",
        "cornerRadius": 0,
        "curveFrom": "{1, 1}",
        "curveMode": 1,
        "curveTo": "{1, 1}",
        "hasCurveFrom": false,
        "hasCurveTo": false,
        "point": "{1, 1}"
      },
      {
        "_class": "curvePoint",
        "cornerRadius": 0,
        "curveFrom": "{1, 0}",
        "curveMode": 1,
        "curveTo": "{1, 0}",
        "hasCurveFrom": false,
        "hasCurveTo": false,
        "point": "{1, 0}"
      }
    ]
  },
  "resizingType": 0,
  "rotation": 0,
  "shouldBreakMaskChain": false
}