{
  "_class": "triangle",
  "booleanOperation": -1,
  "do_objectID": "5127356B-68CC-49F8-B63A-291C215CFF98",
  "edited": true,
  "exportOptions": {
    "_class": "exportOptions",
    "exportFormats": [
    ],
    "includedLayerIds": [
    ],
    "layerOptions": 0,
    "shouldTrim": false
  },
  "frame": {
    "_class": "rect",
    "constrainProportions": false,
    "height": 23.89391326904297,
    "width": 28,
    "x": 0,
    "y": 0
  },
  "isEquilateral": false,
  "isFlippedHorizontal": false,
  "isFlippedVertical": false,
  "isLocked": false,
  "isVisible": true,
  "layerListExpandedType": 0,
  "name": "Path",
  "nameIsFixed": false,
  "path": {
    "_class": "path",
    "isClosed": true,
    "points": [
      {
        "_class": "curvePoint",
        "cornerRadius": 0,
        "curveFrom": "{0.5, 0}",
        "curveMode": 1,
        "curveTo": "{0.5, 0}",
        "hasCurveFrom": false,
        "hasCurveTo": false,
        "point": "{0.5, 0}"
      },
      {
        "_class": "curvePoint",
        "cornerRadius": 0,
        "curveFrom": "{0.83621935634227051, 0.8370332550722055}",
        "curveMode": 1,
        "curveTo": "{1, 0.8370332550722055}",
        "hasCurveFrom": false,
        "hasCurveTo": false,
        "point": "{1, 0.8370332550722055}"
      },
      {
        "_class": "curvePoint",
        "cornerRadius": 0,
        "curveFrom": "{0.15286057335989808, 1}",
        "curveMode": 2,
        "curveTo": "{0.84713942664010189, 1}",
        "hasCurveFrom": true,
        "hasCurveTo": true,
        "point": "{0.5, 1}"
      },
      {
        "_class": "curvePoint",
        "cornerRadius": 0,
        "curveFrom": "{0, 0.8370332550722055}",
        "curveMode": 1,
        "curveTo": "{0.16955268967560402, 0.8370332550722055}",
        "hasCurveFrom": false,
        "hasCurveTo": false,
        "point": "{0, 0.8370332550722055}"
      }
    ]
  },
  "resizingType": 0,
  "rotation": 0,
  "shouldBreakMaskChain": false
}